hfpics/__init__.py
hfpics/core.py
hfpics-0.1.0.dist-info/METADATA
hfpics-0.1.0.dist-info/WHEEL
hfpics-0.1.0.dist-info/top_level.txt
hfpics-0.1.0.dist-info/RECORD
