Metadata-Version: 2.1
Name: hfpics
Version: 0.1.0
Summary: 一个用于从Hugging Face数据集下载图片的Python包
Author-email: shiertier <junjietext@gmail.com>
Project-URL: Homepage, https://github.com/shiertier/hfpics
Project-URL: Documentation, https://github.com/shiertier/hfpics#readme
Project-URL: Repository, https://github.com/shiertier/hfpics.git
Project-URL: Issues, https://github.com/shiertier/hfpics/issues
Keywords: huggingface,datasets,images,download,cache
Classifier: License :: OSI Approved :: MIT License
Classifier: Programming Language :: Python
Classifier: Programming Language :: Python :: 3
Classifier: Programming Language :: Python :: 3.7
Classifier: Programming Language :: Python :: 3.8
Classifier: Programming Language :: Python :: 3.9
Classifier: Programming Language :: Python :: 3.10
Classifier: Programming Language :: Python :: 3.11
Classifier: Topic :: Software Development :: Libraries :: Python Modules
Classifier: Topic :: Multimedia :: Graphics
Requires-Python: >=3.7
Requires-Dist: requests>=2.25.0
Provides-Extra: dev
Requires-Dist: pytest>=6.0; extra == "dev"
Requires-Dist: pytest-cov>=2.0; extra == "dev"
Requires-Dist: black>=22.0; extra == "dev"
Requires-Dist: isort>=5.0; extra == "dev"
Requires-Dist: mypy>=0.900; extra == "dev"
Requires-Dist: build>=0.7.0; extra == "dev"
Requires-Dist: twine>=3.4.0; extra == "dev"
